threadpool/__init__.py
threadpool/_threadpool.py
rythreadpool-1.0.0.dist-info/LICENSE
rythreadpool-1.0.0.dist-info/METADATA
rythreadpool-1.0.0.dist-info/WHEEL
rythreadpool-1.0.0.dist-info/top_level.txt
rythreadpool-1.0.0.dist-info/RECORD
