Metadata-Version: 2.2
Name: rythreadpool
Version: 1.0.0
Summary: Multi-threading library
Author: ryzeon-dev
Project-URL: Homepage, https://github.com/ryzeon-dev/rythreadpool
Classifier: Programming Language :: Python :: 3
Classifier: License :: OSI Approved :: GNU Affero General Public License v3 or later (AGPLv3+)
Requires-Python: >=3.8
License-File: LICENSE
